repogen/__init__.py
repogen/cli.py
repogen/repo_program.py
repogen/custom_resources/__init__.py
repogen/custom_resources/github_action_environment_secret/__init__.py
repogen/custom_resources/github_action_environment_secret/errors.py
repogen/custom_resources/github_action_environment_secret/resource.py
repogen/custom_resources/github_action_environment_secret/secrets_utils.py
repogen/custom_resources/scaffolded_project/__init__.py
repogen/custom_resources/scaffolded_project/github_repo.py
repogen/custom_resources/scaffolded_project/resource.py
repogen-0.0.0.dist-info/METADATA
repogen-0.0.0.dist-info/WHEEL
repogen-0.0.0.dist-info/entry_points.txt
repogen-0.0.0.dist-info/top_level.txt
repogen-0.0.0.dist-info/RECORD
