Metadata-Version: 2.1
Name: repogen
Version: 0.0.0
Home-page: 
Author: 
Author-email: 
License: Proprietary
Project-URL: Documentation, https://docs.rootski.io
Project-URL: Source, https://github.com
Keywords: <Add keywords here>
Classifier: Programming Language :: Python :: 3.7
Classifier: Programming Language :: Python :: 3.8
Classifier: Programming Language :: Python :: 3.9
Classifier: Programming Language :: Python :: 3.10
Requires-Python: >=3.6.*
Requires-Dist: pulumi (<4.0.0,>=3.0.0)
Requires-Dist: pulumi-github
Requires-Dist: pynacl
Requires-Dist: GitPython
Requires-Dist: python-dotenv
Requires-Dist: phitoduck-projen
Requires-Dist: typer
Requires-Dist: rich
Requires-Dist: importlib-metadata ; python_version < "3.8"
Provides-Extra: all
Requires-Dist: pytest ; extra == 'all'
Requires-Dist: pytest-cov ; extra == 'all'
Requires-Dist: pytest-xdist ; extra == 'all'
Provides-Extra: dev
Requires-Dist: pytest ; extra == 'dev'
Requires-Dist: pytest-cov ; extra == 'dev'
Requires-Dist: pytest-xdist ; extra == 'dev'
Provides-Extra: test
Requires-Dist: pytest ; extra == 'test'
Requires-Dist: pytest-cov ; extra == 'test'
Requires-Dist: pytest-xdist ; extra == 'test'
